<profile>

<ReportVersion>
<Version>2023.2</Version>
</ReportVersion>

<UserAssignments>
<unit>ns</unit>
<ProductFamily>virtexuplus</ProductFamily>
<Part>xcu200-fsgd2104-2-e</Part>
<TopModelName>node4_Pipeline_loop15_loop16_loop17</TopModelName>
<TargetClockPeriod>3.33</TargetClockPeriod>
<ClockUncertainty>0.90</ClockUncertainty>
<FlowTarget>vivado</FlowTarget>
</UserAssignments>

<PerformanceEstimates>
<PipelineType>no</PipelineType>
<SummaryOfTimingAnalysis>
<unit>ns</unit>
<EstimatedClockPeriod>2.692</EstimatedClockPeriod>
</SummaryOfTimingAnalysis>
<SummaryOfOverallLatency>
<unit>clock cycles</unit>
<Best-caseLatency>103974</Best-caseLatency>
<Average-caseLatency>103974</Average-caseLatency>
<Worst-caseLatency>103974</Worst-caseLatency>
<Best-caseRealTimeLatency>0.346 ms</Best-caseRealTimeLatency>
<Average-caseRealTimeLatency>0.346 ms</Average-caseRealTimeLatency>
<Worst-caseRealTimeLatency>0.346 ms</Worst-caseRealTimeLatency>
<Interval-min>103974</Interval-min>
<Interval-max>103974</Interval-max>
</SummaryOfOverallLatency>
<SummaryOfLoopLatency>
<loop15_loop16_loop17>
<Slack>2.43</Slack>
<TripCount>103968</TripCount>
<Latency>103972</Latency>
<AbsoluteTimeLatency>346226</AbsoluteTimeLatency>
<PipelineII>1</PipelineII>
<PipelineDepth>6</PipelineDepth>
<InstanceList>
</InstanceList>
</loop15_loop16_loop17>
</SummaryOfLoopLatency>
<SummaryOfViolations>
<IssueType>Timing Violation</IssueType>
<ViolationType>-</ViolationType>
<SourceLocation>src/DepthwiseSeparableConvBlock.cpp:145</SourceLocation>
<SummaryOfLoopViolations>
<loop15_loop16_loop17>
<Name>loop15_loop16_loop17</Name>
<IssueType>-</IssueType>
<ViolationType>-</ViolationType>
<SourceLocation>src/DepthwiseSeparableConvBlock.cpp:143</SourceLocation>
</loop15_loop16_loop17>
</SummaryOfLoopViolations>
</SummaryOfViolations>
</PerformanceEstimates>

<AreaEstimates>
<Resources>
<DSP>1</DSP>
<FF>145</FF>
<LUT>342</LUT>
<BRAM_18K>0</BRAM_18K>
<URAM>0</URAM>
</Resources>
<AvailableResources>
<BRAM_18K>4320</BRAM_18K>
<DSP>6840</DSP>
<FF>2364480</FF>
<LUT>1182240</LUT>
<URAM>960</URAM>
</AvailableResources>
</AreaEstimates>

<InterfaceSummary>
<RtlPorts>
<name>ap_clk</name>
<Object>node4_Pipeline_loop15_loop16_loop17</Object>
<Type>return value</Type>
<Scope></Scope>
<IOProtocol>ap_ctrl_hs</IOProtocol>
<IOConfig></IOConfig>
<Dir>in</Dir>
<Bits>1</Bits>
<Attribute>control</Attribute>
</RtlPorts>
<RtlPorts>
<name>ap_rst</name>
<Object>node4_Pipeline_loop15_loop16_loop17</Object>
<Type>return value</Type>
<Scope></Scope>
<IOProtocol>ap_ctrl_hs</IOProtocol>
<IOConfig></IOConfig>
<Dir>in</Dir>
<Bits>1</Bits>
<Attribute>control</Attribute>
</RtlPorts>
<RtlPorts>
<name>ap_start</name>
<Object>node4_Pipeline_loop15_loop16_loop17</Object>
<Type>return value</Type>
<Scope></Scope>
<IOProtocol>ap_ctrl_hs</IOProtocol>
<IOConfig></IOConfig>
<Dir>in</Dir>
<Bits>1</Bits>
<Attribute>control</Attribute>
</RtlPorts>
<RtlPorts>
<name>ap_done</name>
<Object>node4_Pipeline_loop15_loop16_loop17</Object>
<Type>return value</Type>
<Scope></Scope>
<IOProtocol>ap_ctrl_hs</IOProtocol>
<IOConfig></IOConfig>
<Dir>out</Dir>
<Bits>1</Bits>
<Attribute>control</Attribute>
</RtlPorts>
<RtlPorts>
<name>ap_idle</name>
<Object>node4_Pipeline_loop15_loop16_loop17</Object>
<Type>return value</Type>
<Scope></Scope>
<IOProtocol>ap_ctrl_hs</IOProtocol>
<IOConfig></IOConfig>
<Dir>out</Dir>
<Bits>1</Bits>
<Attribute>control</Attribute>
</RtlPorts>
<RtlPorts>
<name>ap_ready</name>
<Object>node4_Pipeline_loop15_loop16_loop17</Object>
<Type>return value</Type>
<Scope></Scope>
<IOProtocol>ap_ctrl_hs</IOProtocol>
<IOConfig></IOConfig>
<Dir>out</Dir>
<Bits>1</Bits>
<Attribute>control</Attribute>
</RtlPorts>
<RtlPorts>
<name>v60_address0</name>
<Object>v60</Object>
<Type>array</Type>
<Scope></Scope>
<IOProtocol>ap_memory</IOProtocol>
<IOConfig></IOConfig>
<Dir>out</Dir>
<Bits>17</Bits>
<Attribute>address</Attribute>
</RtlPorts>
<RtlPorts>
<name>v60_ce0</name>
<Object>v60</Object>
<Type>array</Type>
<Scope></Scope>
<IOProtocol>ap_memory</IOProtocol>
<IOConfig></IOConfig>
<Dir>out</Dir>
<Bits>1</Bits>
<Attribute>control</Attribute>
</RtlPorts>
<RtlPorts>
<name>v60_we0</name>
<Object>v60</Object>
<Type>array</Type>
<Scope></Scope>
<IOProtocol>ap_memory</IOProtocol>
<IOConfig></IOConfig>
<Dir>out</Dir>
<Bits>1</Bits>
<Attribute>control</Attribute>
</RtlPorts>
<RtlPorts>
<name>v60_d0</name>
<Object>v60</Object>
<Type>array</Type>
<Scope></Scope>
<IOProtocol>ap_memory</IOProtocol>
<IOConfig></IOConfig>
<Dir>out</Dir>
<Bits>32</Bits>
<Attribute>data</Attribute>
</RtlPorts>
</InterfaceSummary>

</profile>
