{
  "Config": {
    "Model": "ResMLP",
    "Benchmark": "mlps",
    "DSPs Limit": 512,
    "Tiling Limit": 16,
    "Debug Point": 14,
    "Combined Optimization": 0,
    "Permutation Optimization": 0,
    "Parallelization Optimization": 0,
    "Time Limit (mins)": 5
  },
  "Compilation Time (s)": 0.8559327125549316,
  "DSP Utilization": null,
  "Sequential Cycles": 18359291,
  "Parallel Cycles": null,
  "Combined Cycles": null,
  "Permutation Design Space": 1327104,
  "Parallelization Design Space": 2067326501556060160,
  "Combined Design Space": 2743557269521053662576640,
  "Permutation Search Time (s)": null,
  "Parallelization Search Time (s)": null,
  "Combined Search Time (s)": null,
  "Status": "Success"
}